{
  "openapi": "3.0.3",
  "info": {
    "title": "User Management API",
    "description": "API for managing user profiles and role assignments",
    "version": "1.0.0",
    "contact": {
      "name": "Development Team",
      "email": "dev@example.com"
    }
  },
  "servers": [
    {
      "url": "https://api.example.com/v1",
      "description": "Production server"
    },
    {
      "url": "https://staging-api.example.com/v1",
      "description": "Staging server"
    }
  ],
  "paths": {
    "/api/users": {
      "post": {
        "summary": "Create User Profile",
        "description": "Creates a new user profile with the provided information",
        "tags": ["User Management"],
        "requestBody": {
          "required": true,
          "content": {
            "application/json": {
              "schema": {
                "$ref": "#/components/schemas/CreateUserRequest"
              }
            }
          }
        },
        "responses": {
          "201": {
            "description": "User created successfully",
            "content": {
              "application/json": {
                "schema": {
                  "$ref": "#/components/schemas/UserResponse"
                }
              }
            }
          },
          "400": {
            "description": "Invalid input data",
            "content": {
              "application/json": {
                "schema": {
                  "$ref": "#/components/schemas/ErrorResponse"
                }
              }
            }
          },
          "409": {
            "description": "Email already exists",
            "content": {
              "application/json": {
                "schema": {
                  "$ref": "#/components/schemas/ErrorResponse"
                }
              }
            }
          }
        }
      }
    },
    "/api/users/{userId}": {
      "get": {
        "summary": "Get User Profile",
        "description": "Retrieves the profile information for a specific user",
        "tags": ["User Management"],
        "parameters": [
          {
            "name": "userId",
            "in": "path",
            "required": true,
            "schema": {
              "type": "string",
              "format": "uuid"
            }
          }
        ],
        "responses": {
          "200": {
            "description": "User profile retrieved successfully",
            "content": {
              "application/json": {
                "schema": {
                  "$ref": "#/components/schemas/UserProfileResponse"
                }
              }
            }
          },
          "404": {
            "description": "User not found",
            "content": {
              "application/json": {
                "schema": {
                  "$ref": "#/components/schemas/ErrorResponse"
                }
              }
            }
          }
        }
      },
      "put": {
        "summary": "Update User Profile",
        "description": "Updates the profile information for a specific user",
        "tags": ["User Management"],
        "parameters": [
          {
            "name": "userId",
            "in": "path",
            "required": true,
            "schema": {
              "type": "string",
              "format": "uuid"
            }
          }
        ],
        "requestBody": {
          "required": true,
          "content": {
            "application/json": {
              "schema": {
                "$ref": "#/components/schemas/UpdateUserRequest"
              }
            }
          }
        },
        "responses": {
          "200": {
            "description": "User profile updated successfully",
            "content": {
              "application/json": {
                "schema": {
                  "$ref": "#/components/schemas/UserResponse"
                }
              }
            }
          },
          "400": {
            "description": "Invalid input data",
            "content": {
              "application/json": {
                "schema": {
                  "$ref": "#/components/schemas/ErrorResponse"
                }
              }
            }
          },
          "404": {
            "description": "User not found",
            "content": {
              "application/json": {
                "schema": {
                  "$ref": "#/components/schemas/ErrorResponse"
                }
              }
            }
          }
        }
      }
    },
    "/api/users/{userId}/roles": {
      "get": {
        "summary": "Get User Roles",
        "description": "Retrieves all roles assigned to a specific user",
        "tags": ["Role Management"],
        "parameters": [
          {
            "name": "userId",
            "in": "path",
            "required": true,
            "schema": {
              "type": "string",
              "format": "uuid"
            }
          }
        ],
        "responses": {
          "200": {
            "description": "User roles retrieved successfully",
            "content": {
              "application/json": {
                "schema": {
                  "$ref": "#/components/schemas/UserRolesResponse"
                }
              }
            }
          },
          "404": {
            "description": "User not found",
            "content": {
              "application/json": {
                "schema": {
                  "$ref": "#/components/schemas/ErrorResponse"
                }
              }
            }
          }
        }
      },
      "post": {
        "summary": "Assign Role to User",
        "description": "Assigns a specific role to a user",
        "tags": ["Role Management"],
        "parameters": [
          {
            "name": "userId",
            "in": "path",
            "required": true,
            "schema": {
              "type": "string",
              "format": "uuid"
            }
          }
        ],
        "requestBody": {
          "required": true,
          "content": {
            "application/json": {
              "schema": {
                "$ref": "#/components/schemas/AssignRoleRequest"
              }
            }
          }
        },
        "responses": {
          "201": {
            "description": "Role assigned successfully",
            "content": {
              "application/json": {
                "schema": {
                  "$ref": "#/components/schemas/RoleAssignmentResponse"
                }
              }
            }
          },
          "400": {
            "description": "Invalid input data",
            "content": {
              "application/json": {
                "schema": {
                  "$ref": "#/components/schemas/ErrorResponse"
                }
              }
            }
          },
          "404": {
            "description": "User or role not found",
            "content": {
              "application/json": {
                "schema": {
                  "$ref": "#/components/schemas/ErrorResponse"
                }
              }
            }
          },
          "409": {
            "description": "Role already assigned to user",
            "content": {
              "application/json": {
                "schema": {
                  "$ref": "#/components/schemas/ErrorResponse"
                }
              }
            }
          }
        }
      }
    },
    "/api/users/{userId}/roles/{roleId}": {
      "delete": {
        "summary": "Remove Role from User",
        "description": "Removes a specific role from a user",
        "tags": ["Role Management"],
        "parameters": [
          {
            "name": "userId",
            "in": "path",
            "required": true,
            "schema": {
              "type": "string",
              "format": "uuid"
            }
          },
          {
            "name": "roleId",
            "in": "path",
            "required": true,
            "schema": {
              "type": "string",
              "format": "uuid"
            }
          }
        ],
        "responses": {
          "200": {
            "description": "Role removed successfully",
            "content": {
              "application/json": {
                "schema": {
                  "$ref": "#/components/schemas/SuccessResponse"
                }
              }
            }
          },
          "404": {
            "description": "User, role, or assignment not found",
            "content": {
              "application/json": {
                "schema": {
                  "$ref": "#/components/schemas/ErrorResponse"
                }
              }
            }
          }
        }
      }
    }
  },
  "components": {
    "schemas": {
      "CreateUserRequest": {
        "type": "object",
        "required": ["email", "password", "firstName", "lastName"],
        "properties": {
          "email": {
            "type": "string",
            "format": "email",
            "description": "User's email address"
          },
          "password": {
            "type": "string",
            "minLength": 8,
            "description": "User's password"
          },
          "firstName": {
            "type": "string",
            "description": "User's first name"
          },
          "lastName": {
            "type": "string",
            "description": "User's last name"
          }
        }
      },
      "UpdateUserRequest": {
        "type": "object",
        "properties": {
          "firstName": {
            "type": "string",
            "description": "User's first name"
          },
          "lastName": {
            "type": "string",
            "description": "User's last name"
          },
          "phone": {
            "type": "string",
            "description": "User's phone number"
          },
          "avatar": {
            "type": "string",
            "description": "URL to user's avatar image"
          }
        }
      },
      "AssignRoleRequest": {
        "type": "object",
        "required": ["roleId"],
        "properties": {
          "roleId": {
            "type": "string",
            "format": "uuid",
            "description": "ID of the role to assign"
          }
        }
      },
      "UserResponse": {
        "type": "object",
        "properties": {
          "id": {
            "type": "string",
            "format": "uuid",
            "description": "User's unique identifier"
          },
          "email": {
            "type": "string",
            "format": "email",
            "description": "User's email address"
          },
          "verified": {
            "type": "boolean",
            "description": "Email verification status"
          },
          "createdAt": {
            "type": "string",
            "format": "date-time",
            "description": "Account creation timestamp"
          },
          "updatedAt": {
            "type": "string",
            "format": "date-time",
            "description": "Last update timestamp"
          }
        }
      },
      "UserProfileResponse": {
        "allOf": [
          {
            "$ref": "#/components/schemas/UserResponse"
          },
          {
            "type": "object",
            "properties": {
              "firstName": {
                "type": "string",
                "description": "User's first name"
              },
              "lastName": {
                "type": "string",
                "description": "User's last name"
              },
              "phone": {
                "type": "string",
                "description": "User's phone number"
              },
              "avatar": {
                "type": "string",
                "description": "URL to user's avatar image"
              },
              "roles": {
                "type": "array",
                "items": {
                  "type": "string"
                },
                "description": "List of role names assigned to the user"
              }
            }
          }
        ]
      },
      "UserRolesResponse": {
        "type": "object",
        "properties": {
          "roles": {
            "type": "array",
            "items": {
              "$ref": "#/components/schemas/RoleInfo"
            }
          }
        }
      },
      "RoleInfo": {
        "type": "object",
        "properties": {
          "id": {
            "type": "string",
            "format": "uuid",
            "description": "Role's unique identifier"
          },
          "name": {
            "type": "string",
            "description": "Role name"
          },
          "description": {
            "type": "string",
            "description": "Role description"
          },
          "assignedAt": {
            "type": "string",
            "format": "date-time",
            "description": "When the role was assigned to the user"
          }
        }
      },
      "RoleAssignmentResponse": {
        "type": "object",
        "properties": {
          "userId": {
            "type": "string",
            "format": "uuid",
            "description": "User's unique identifier"
          },
          "roleId": {
            "type": "string",
            "format": "uuid",
            "description": "Role's unique identifier"
          },
          "assignedAt": {
            "type": "string",
            "format": "date-time",
            "description": "When the role was assigned"
          }
        }
      },
      "SuccessResponse": {
        "type": "object",
        "properties": {
          "message": {
            "type": "string",
            "description": "Success message"
          }
        }
      },
      "ErrorResponse": {
        "type": "object",
        "properties": {
          "error": {
            "type": "string",
            "description": "Error message"
          },
          "code": {
            "type": "string",
            "description": "Error code"
          },
          "details": {
            "type": "object",
            "description": "Additional error details"
          }
        }
      }
    },
    "securitySchemes": {
      "bearerAuth": {
        "type": "http",
        "scheme": "bearer",
        "bearerFormat": "JWT"
      }
    }
  },
  "security": [
    {
      "bearerAuth": []
    }
  ],
  "tags": [
    {
      "name": "User Management",
      "description": "Operations for managing user profiles"
    },
    {
      "name": "Role Management",
      "description": "Operations for managing user role assignments"
    }
  ]
}
